examples/image_gen.py
examples/kivy_basic.py
examples/loading_indicator.py
materialshapes/__init__.py
materialshapes/corner_rounding.py
materialshapes/cubic.py
materialshapes/feature_mapping.py
materialshapes/features.py
materialshapes/float_mapping.py
materialshapes/kivy_widget.py
materialshapes/material_shapes.py
materialshapes/morph.py
materialshapes/point.py
materialshapes/polygon_measure.py
materialshapes/rounded_polygon.py
materialshapes/utils.py
materialshapes-0.2.dist-info/licenses/LICENSE
materialshapes-0.2.dist-info/METADATA
materialshapes-0.2.dist-info/WHEEL
materialshapes-0.2.dist-info/top_level.txt
materialshapes-0.2.dist-info/RECORD
