Metadata-Version: 2.4
Name: materialshapes
Version: 0.2
Summary: Material shapes in pure python.
Author-email: Ansh Dadwal <anshdadwal298@gmail.com>
License-Expression: MIT
Requires-Python: >3.8
License-File: LICENSE
Requires-Dist: kivy
Requires-Dist: pycairo
Requires-Dist: pillow
Dynamic: license-file
